MANIFEST.in
setup.py
dappr/__init__.py
dappr/admin.py
dappr/forms.py
dappr/models.py
dappr/tests.py
dappr/urls.py
dappr/views.py
dappr.egg-info/PKG-INFO
dappr.egg-info/SOURCES.txt
dappr.egg-info/dependency_links.txt
dappr.egg-info/requires.txt
dappr.egg-info/top_level.txt
dappr/migrations/0001_initial.py
dappr/migrations/0002_auto_20160207_1640.py
dappr/migrations/0003_auto_20160213_0010.py
dappr/migrations/0004_registrationprofile_approved.py
dappr/migrations/0005_registrationprofile_active.py
dappr/migrations/0006_auto_20160222_0122.py
dappr/migrations/0007_auto_20160222_0123.py
dappr/migrations/__init__.py
dappr/templates/registration/admin_notification_email.html
dappr/templates/registration/admin_notification_email_subject.txt
dappr/templates/registration/confirmation_email.html
dappr/templates/registration/confirmation_email_subject.txt
dappr/templates/registration/email_confirmed.html
dappr/templates/registration/invalid_confirmation_code.html
dappr/templates/registration/registration_form.html
dappr/templates/registration/rejection_email.html
dappr/templates/registration/rejection_email_subject.txt
dappr/templates/registration/success_email.html
dappr/templates/registration/success_email_subject.txt