Metadata-Version: 1.0
Name: dappr
Version: 0.7
Summary: Django app for registration, with an approval step.
Home-page: https://github.com/millanp/dappr
Author: Millan Philipose
Author-email: millan.j.philipose@gmail.com
License: MIT
Platform: UNKNOWN
